linkml_solr/__init__.py
linkml_solr/cli.py
linkml_solr/mapper.py
linkml_solr/query.py
linkml_solr/solrmodel.py
linkml_solr/solrschema.py
linkml_solr/solrschemagen.py
linkml_solr/utils/__init__.py
linkml_solr/utils/golr_schema_utils.py
linkml_solr/utils/solr_bulkload.py
linkml_solr-0.2.0.dist-info/METADATA
linkml_solr-0.2.0.dist-info/WHEEL
linkml_solr-0.2.0.dist-info/entry_points.txt
linkml_solr-0.2.0.dist-info/RECORD
