Metadata-Version: 2.3
Name: linkml-solr
Version: 0.2.0
Summary: 
Author: Chris Mungall
Author-email: cjm@berkeleybop.org
Requires-Python: >=3.8.1,<4.0.0
Classifier: Programming Language :: Python :: 3
Classifier: Programming Language :: Python :: 3.9
Classifier: Programming Language :: Python :: 3.10
Classifier: Programming Language :: Python :: 3.11
Classifier: Programming Language :: Python :: 3.12
Classifier: Programming Language :: Python :: 3.13
Requires-Dist: duckdb
Requires-Dist: jsonasobj (>=1.3.1,<2.0.0)
Requires-Dist: linkml (>=1.7.0,<2.0.0)
Requires-Dist: linkml-dataops (>=0.1.0,<0.2.0)
Requires-Dist: linkml-runtime (>=1.7.4)
Requires-Dist: pysolr (>=3.9.0,<4.0.0)
Requires-Dist: requests (>=2.25.0,<3.0.0)
